Metadata-Version: 2.1
Name: co3
Version: 0.6.3
Summary: Lightweight Python ORM for hierarchical storage management
Author-email: Sam Griesemer <samgriesemer+git@gmail.com>
Project-URL: Homepage, https://doc.olog.io/co3
Project-URL: Documentation, https://doc.olog.io/co3
Project-URL: Repository, https://git.olog.io/olog/co3
Project-URL: Issues, https://git.olog.io/olog/co3/issues
Keywords: database,orm
Classifier: Programming Language :: Python :: 3.12
Classifier: License :: OSI Approved :: MIT License
Classifier: Operating System :: OS Independent
Classifier: Development Status :: 3 - Alpha
Classifier: Intended Audience :: Developers
Requires-Python: >=3.12
License-File: LICENSE
Requires-Dist: tqdm
Requires-Dist: wcmatch
Requires-Dist: numpy
Requires-Dist: sqlalchemy
Requires-Dist: colorama
Provides-Extra: docs
Requires-Dist: sphinx ; extra == 'docs'
Requires-Dist: sphinx-togglebutton ; extra == 'docs'
Requires-Dist: sphinx-autodoc-typehints ; extra == 'docs'
Requires-Dist: furo ; extra == 'docs'
Requires-Dist: myst-parser ; extra == 'docs'
Provides-Extra: tests
Requires-Dist: pytest ; extra == 'tests'
